umarkdown-1.6.dist-info/RECORD
umarkdown-1.6.dist-info/entry_points.txt
umarkdown-1.6.dist-info/WHEEL
umarkdown-1.6.dist-info/METADATA
umarkdown-1.6.dist-info/LICENSE.md
umarkdown-1.6.dist-info/top_level.txt
umarkdown/cli.py
umarkdown/py.typed
umarkdown/_internal.c
umarkdown/_internal.abi3.so
umarkdown/_internal.pyi
umarkdown/__init__.py
