Metadata-Version: 2.1
Name: umarkdown
Version: 1.6
Summary: Python wrapper of Markdown using CMark.
Home-page: https://umarkdown.netlify.app/
Author: Kumar Aditya
Author-email: 
License: BSD License
Keywords: Markdown,CMark
Classifier: Programming Language :: C
Classifier: Programming Language :: Python
Classifier: Programming Language :: Python :: 3
Classifier: Programming Language :: Python :: 3.8
Classifier: Programming Language :: Python :: 3.9
Classifier: Programming Language :: Python :: 3 :: Only
Classifier: Programming Language :: Python :: Implementation :: CPython
Classifier: Operating System :: OS Independent
Classifier: Topic :: Internet :: WWW/HTTP :: Site Management
Classifier: Topic :: Software Development :: Documentation
Classifier: Topic :: Text Processing :: Filters
Classifier: Topic :: Text Processing :: Markup :: HTML
Classifier: Topic :: Text Processing :: Markup :: Markdown
Classifier: License :: OSI Approved :: BSD License
Requires-Python: >=3.8
License-File: LICENSE.md
Provides-Extra: cli
Requires-Dist: click (==8.0.3) ; extra == 'cli'
